plastexdepgraph/__init__.py
plastexdepgraph/Packages/depgraph.py
plastexdepgraph/Packages/renderer_templates/depgraph.jinja2s
plastexdepgraph/static/d3-graphviz.js
plastexdepgraph/static/d3-graphviz.js.map
plastexdepgraph/static/d3.min.js
plastexdepgraph/static/dep_graph.css
plastexdepgraph/static/expatlib.wasm
plastexdepgraph/static/graphvizlib.wasm
plastexdepgraph/static/hpcc.min.js
plastexdepgraph/templates/dep_graph.html
plastexdepgraph-0.0.4.dist-info/LICENSE
plastexdepgraph-0.0.4.dist-info/METADATA
plastexdepgraph-0.0.4.dist-info/NOTICE
plastexdepgraph-0.0.4.dist-info/WHEEL
plastexdepgraph-0.0.4.dist-info/top_level.txt
plastexdepgraph-0.0.4.dist-info/RECORD
