Metadata-Version: 2.1
Name: plastexdepgraph
Version: 0.0.4
Summary: Dependency graph plugin for plasTeX.
Home-page: https://github.com/PatrickMassot/plastexdepgraph
Author: Patrick Massot
Classifier: Programming Language :: Python :: 3
Classifier: License :: OSI Approved :: MIT License
Classifier: Operating System :: OS Independent
Requires-Python: >=3.7
License-File: LICENSE
License-File: NOTICE
Requires-Dist: plasTeX>=3.1
Requires-Dist: pygraphviz
